setup.py
tildetown/__init__.py
tildetown/app.py
tildetown/mustache.py
tildetown/stats.py
tildetown/util.py
tildetown.egg-info/PKG-INFO
tildetown.egg-info/SOURCES.txt
tildetown.egg-info/dependency_links.txt
tildetown.egg-info/requires.txt
tildetown.egg-info/top_level.txt