Metadata-Version: 1.1
Name: tildetown
Version: 0.0.2
Summary: python stuf for tilde.town
Home-page: https://github.com/tildetown/tildetown-scripts
Author: vilmibm shaksfrpease
Author-email: nks@lambdaphil.es
License: GPL
Keywords: community
Platform: UNKNOWN
Classifier: Development Status :: 3 - Alpha
Classifier: Intended Audience :: Other Audience
Classifier: Topic :: Artistic Software
Classifier: License :: OSI Approved :: GNU Lesser General Public License v3 (LGPLv3)
